stdp/__init__.py
stdp/admin.py
stdp/auth.py
stdp/client.py
stdp/database.py
stdp/main.py
stdp/ui/AddDialog.ui
stdp/ui/AuthWindow.ui
stdp/ui/ClientWindow.ui
stdp/ui/MainWindow.ui
stdp/ui/__init__.py
stdp-0.3.0.dist-info/LICENSE
stdp-0.3.0.dist-info/METADATA
stdp-0.3.0.dist-info/WHEEL
stdp-0.3.0.dist-info/entry_points.txt
stdp-0.3.0.dist-info/top_level.txt
stdp-0.3.0.dist-info/RECORD
