Metadata-Version: 2.1
Name: stdp
Version: 0.3.0
Summary: Hotel Management System - PyQt6-based hotel management application
Home-page: https://github.com/willalone/std
Author: willalone
License: MIT
Classifier: Development Status :: 3 - Alpha
Classifier: Intended Audience :: Developers
Classifier: License :: OSI Approved :: MIT License
Classifier: Programming Language :: Python :: 3
Classifier: Programming Language :: Python :: 3.8
Classifier: Programming Language :: Python :: 3.9
Classifier: Programming Language :: Python :: 3.10
Classifier: Programming Language :: Python :: 3.11
Classifier: Programming Language :: Python :: 3.12
Requires-Python: >=3.8
Requires-Dist: PyQt6>=6.0.0
Requires-Dist: pymysql>=1.0.0
